cp4py/__init__.py
cp4py/core/.save.log
cp4py/core/__init__.py
cp4py/core/expr.py
cp4py/core/var.py
cp4py/translators/.save.log
cp4py/translators/__init__.py
cp4py/translators/base.py
cp4py/translators/cplex.py
cp4py/translators/cpoptimizer.py
cp4py/translators/cvc5.py
cp4py/translators/gurobi.py
cp4py/translators/ortools.py
cp4py/translators/scip.py
cp4py/translators/z3.py
cp4py-0.1.1.dist-info/METADATA
cp4py-0.1.1.dist-info/WHEEL
cp4py-0.1.1.dist-info/RECORD
