Metadata-Version: 2.4
Name: cp4py
Version: 0.1.1
Summary: Constraint Programming language and translator for Python
License: MIT
Keywords: constraint-programming,optimization,or-tools,scip,solver,z3
Classifier: License :: OSI Approved :: MIT License
Classifier: Programming Language :: Python :: 3
Classifier: Programming Language :: Python :: 3.10
Classifier: Programming Language :: Python :: 3.11
Classifier: Programming Language :: Python :: 3.12
Classifier: Topic :: Scientific/Engineering :: Mathematics
Requires-Python: >=3.10
Provides-Extra: cplex
Requires-Dist: docplex>=2.23; extra == 'cplex'
Provides-Extra: cpoptimizer
Requires-Dist: docplex>=2.23; extra == 'cpoptimizer'
Provides-Extra: cvc5
Requires-Dist: cvc5>=1.0; extra == 'cvc5'
Provides-Extra: dev
Requires-Dist: pytest>=8.0; extra == 'dev'
Provides-Extra: gurobi
Requires-Dist: gurobipy>=10.0; extra == 'gurobi'
Provides-Extra: ortools
Requires-Dist: ortools>=9.0; extra == 'ortools'
Provides-Extra: scip
Requires-Dist: pyscipopt>=4.0; extra == 'scip'
Provides-Extra: z3
Requires-Dist: z3-solver>=4.0; extra == 'z3'
